porfavor/__init__.py
porfavor/client.py
porfavor/server/__init__.py
porfavor/server/api.py
porfavor/server/main.py
porfavor/server/static/bundle.js
porfavor/server/static/bundle.js.map
porfavor/server/static/fonts/Roboto-Regular.ttf
porfavor/server/static/img/Background.png
porfavor/server/static/img/project_icon.png
porfavor/server/static/img/search.svg
porfavor/server/templates/__init__.py
porfavor/server/templates/index.html
porfavor-0.6.0.dist-info/LICENSE
porfavor-0.6.0.dist-info/METADATA
porfavor-0.6.0.dist-info/WHEEL
porfavor-0.6.0.dist-info/entry_points.txt
porfavor-0.6.0.dist-info/top_level.txt
porfavor-0.6.0.dist-info/RECORD
