Metadata-Version: 2.1
Name: porfavor
Version: 0.6.0
Summary: Publishing static documentation the easy way
Home-page: https://github.com/osherdp/porfavor
Author: osherdp
Author-email: osherdepaz@gmail.com
License: UNKNOWN
Platform: UNKNOWN
Classifier: Programming Language :: Python :: 2
Classifier: Programming Language :: Python :: 2.7
Classifier: Programming Language :: Python :: 3
Classifier: Programming Language :: Python :: 3.5
Classifier: Programming Language :: Python :: 3.6
Classifier: License :: OSI Approved :: MIT License
Classifier: Operating System :: OS Independent
Requires-Python: >=2.7,!=3.0.*,!=3.1.*,!=3.2.*,!=3.3.*,!=3.4.*
Requires-Dist: flask
Requires-Dist: click
Requires-Dist: future
Requires-Dist: requests
Requires-Dist: requests-toolbelt
Provides-Extra: dev
Requires-Dist: flake8; extra == 'dev'
Requires-Dist: pylint; extra == 'dev'
